alarmix/client/__init__.py
alarmix/client/main.py
alarmix/daemon/__init__.py
alarmix/daemon/alarm_manager.py
alarmix/daemon/buzzer.py
alarmix/daemon/main.py
alarmix/daemon/server.py
alarmix/exceptions.py
alarmix/schema.py
alarmix/utils.py
alarmix-0.8.11.dist-info/entry_points.txt
alarmix-0.8.11.dist-info/WHEEL
alarmix-0.8.11.dist-info/METADATA
alarmix-0.8.11.dist-info/RECORD
