Metadata-Version: 2.1
Name: alarmix
Version: 0.8.11
Summary: Alarm manager server and client
Home-page: https://github.com/s3rius/alarmix
Keywords: Poetry,Alarm,Unix sockets
Author: Pavel Kirilin
Author-email: win10@list.ru
Requires-Python: >=3.8,<4.0
Classifier: Operating System :: POSIX :: Linux
Classifier: Programming Language :: Python :: 3
Classifier: Programming Language :: Python :: 3.8
Classifier: Programming Language :: Python :: 3.9
Classifier: Topic :: Utilities
Requires-Dist: daemonize (>=2.5.0,<3.0.0)
Requires-Dist: loguru (>=0.5.3,<0.6.0)
Requires-Dist: prettytable (>=2.0.0,<3.0.0)
Requires-Dist: pydantic (>=1.7.2,<2.0.0)
Project-URL: Repository, https://github.com/s3rius/alarmix
